pbpilot/__init__.py
pbpilot/my_module.py
pbpilot-0.0.0.dist-info/METADATA
pbpilot-0.0.0.dist-info/WHEEL
pbpilot-0.0.0.dist-info/top_level.txt
pbpilot-0.0.0.dist-info/RECORD
